Metadata-Version: 2.1
Name: stream-framework-plus
Version: 1.4.0.3
Summary: Stream Framework allows you to build complex feed and caching structures using Redis.
Home-page: https://github.com/tschellenbach/Stream-Framework/
Author: Thierry Schellenbach
Author-email: thierryschellenbach@gmail.com
License: UNKNOWN
Platform: UNKNOWN
Classifier: Intended Audience :: Developers
Classifier: Intended Audience :: System Administrators
Classifier: Operating System :: OS Independent
Classifier: Topic :: Software Development
Classifier: Development Status :: 5 - Production/Stable
Classifier: License :: OSI Approved :: GNU General Public License (GPL)
Classifier: Natural Language :: English
Classifier: Programming Language :: Python
Classifier: Programming Language :: Python :: 2.7
Classifier: Programming Language :: Python :: 3.7
Classifier: Topic :: Scientific/Engineering :: Mathematics
Classifier: Topic :: Software Development :: Libraries :: Python Modules
Classifier: Framework :: Django
Requires-Dist: celery (>=3.0.0)
Requires-Dist: six
Provides-Extra: cassandra
Requires-Dist: cassandra-driver (>=2.7.2) ; extra == 'cassandra'
Provides-Extra: redis
Requires-Dist: redis (>=3.0) ; extra == 'redis'
Provides-Extra: test
Requires-Dist: Django (>=1.3) ; extra == 'test'
Requires-Dist: mock ; extra == 'test'
Requires-Dist: pep8 ; extra == 'test'
Requires-Dist: unittest2 ; extra == 'test'
Requires-Dist: pytest ; extra == 'test'
